py/exp1/test_module/ref_module.v
module ref_module (
    input clk,
    input rstn,
    input in, 
    output reg out
);
always@(posedge clk or negedge rstn) begin
    if(~rstn) out <= 0;
	else out <= in ^ out;    
end
endmodule

backend/exp1/test_module/user_module.v
module xor_trigger (
    input clk,
    input rstn,
    input in, 
    output reg out
);
always@(posedge clk or negedge rstn) begin
    if(~rstn) out <= 0;
	else out <= in ^ out;    
end
endmodule

backend/exp1/test_bench/test_bench.v
`timescale 1ns/1ps
module test_bench(); //test_bench模块名不可更改，tcl脚本需要识别
reg clk;
reg rstn;
reg refrence_in;
wire your_out, refrence_out;
wire mismatch = (refrence_out !== your_out); //强判断，x或z也会判断是否相等
//mismatch信号不可省略，mismatch的逻辑由test_bench决定，tcl脚本识别mismatch信号，如果在仿真过程中不为0则波形不匹配。

initial clk = 0;
always #10 clk = ~clk;

initial begin
    $dumpfile ("waveform.vcd"); //生成波形文件
    $dumpvars (0,test_bench.clk,test_bench.rstn,test_bench.refrence_in,test_bench.your_out,test_bench.refrence_out,test_bench.mismatch); //自行按顺序添加需要记录的波形
    rstn = 1;
    refrence_in = 0;
    #30 $dumpon; //开始记录波形
    #10 rstn = 0;
    #50 rstn = 1;
    #25 refrence_in = 1;
    #25 refrence_in = 0;
    #25 refrence_in = 1;
    #25 refrence_in = 0;
    #25 $dumpoff; //结束记录波形
    $stop(); //必须使用stop停止仿真，使用finish会强制关闭进程
end


xor_trigger user_module_inst(
    .clk    (clk        ),
    .rstn   (rstn       ),
    .in     (refrence_in),
    .out    (your_out   )
);
ref_module ref_module_inst(
    .clk    (clk         ),
    .rstn   (rstn        ),
    .in     (refrence_in ),
    .out    (refrence_out)
);

endmodule //test_bencch

backend/sub_data/wave_5.vcd
$date
	Sat Apr 12 18:48:04 2025
$end
$version
	Icarus Verilog
$end
$timescale
	1ps
$end
$scope module test_bench $end
$var reg 1 ! clk $end
$upscope $end
$scope module test_bench $end
$var reg 1 " rstn $end
$upscope $end
$scope module test_bench $end
$var reg 1 # refrence_in $end
$upscope $end
$scope module test_bench $end
$var wire 1 $ your_out $end
$upscope $end
$scope module test_bench $end
$var wire 1 % refrence_out $end
$upscope $end
$scope module test_bench $end
$var wire 1 & mismatch $end
$upscope $end
$enddefinitions $end
#0
$dumpvars
0&
x%
x$
0#
1"
0!
$end
#10000
1!
#20000
0!
#30000
1!
#40000
1&
0%
0!
0"
#50000
1!
#60000
0!
#70000
1!
#80000
0!
#90000
1!
1"
#100000
0!
#110000
1!
#115000
1#
#120000
0!
#130000
1%
1!
#140000
0!
0#
#150000
1!
#160000
0!
#165000
1#
#170000
0%
1!
#180000
0!
#190000
1!
0#
#200000
0!
#210000
1!
#215000
$dumpoff
x&
x%
x$
x#
x"
x!
$end
