py/exp1/test_module/ref_module.v
module ref_module (
    input clk,
    input rstn,
    input in, 
    output reg out
);
always@(posedge clk or negedge rstn) begin
    if(~rstn) out <= 0;
	else out <= in ^ out;    
end
endmodule

py/exp1/test_module/user_module.v
module user_module (
    input clk,
    input rstn,
    input in, 
    output reg out
);
always@(posedge clk or negedge rstn) begin
    if(~rstn) out <= 0;
	else out <= in ^ out;
end
endmodule

py/exp1/test_bench/test_bench.v
`timescale 1ns/1ps
module test_bench();
reg clk;
reg rstn;
reg refrence_in;
wire your_out, refrence_out;
wire mismath_out = (refrence_out !== your_out); //强判断，x或z也会判断是否相等

initial clk = 0;
always #10 clk = ~clk;

initial begin
    $dumpfile ("waveform.vcd");
    $dumpvars (0,test_bench.clk,test_bench.rstn,test_bench.refrence_in,test_bench.your_out,test_bench.refrence_out,test_bench.mismath_out);
    rstn = 1;
    refrence_in = 0;
    #30 $dumpon;
    #10 rstn = 0;
    #50 rstn = 1;
    #25 refrence_in = 1;
    #25 refrence_in = 0;
    #25 refrence_in = 1;
    #25 refrence_in = 0;
    #25 $dumpoff;
    $stop();
end


user_module user_module_inst(
    .clk    (clk        ),
    .rstn   (rstn       ),
    .in     (refrence_in),
    .out    (your_out   )
);
ref_module ref_module_inst(
    .clk    (clk         ),
    .rstn   (rstn       ),
    .in     (refrence_in ),
    .out    (refrence_out)
);

endmodule //test_bencch

py/exp1/sim_project/waveform.vcd
$date
	Thu Apr 10 20:07:42 2025
$end
$version
	ModelSim Version 2020.4
$end
$timescale
	1ps
$end

$scope module test_bench $end
$var reg 1 ! clk $end
$var reg 1 " rstn $end
$var reg 1 # refrence_in $end
$var wire 1 $ your_out $end
$var wire 1 % refrence_out $end
$var wire 1 & mismath_out $end
$upscope $end
$enddefinitions $end
#0
$dumpvars
0!
1"
0#
x$
x%
0&
$end
#10000
1!
#20000
0!
#30000
1!
#40000
0"
0!
0%
0$
#50000
1!
#60000
0!
#70000
1!
#80000
0!
#90000
1"
1!
#100000
0!
#110000
1!
#115000
1#
#120000
0!
#130000
1!
1%
1$
#140000
0#
0!
#150000
1!
#160000
0!
#165000
1#
#170000
1!
0%
1&
#180000
0!
#190000
0#
1!
#200000
0!
#210000
1!
#215000
$dumpoff
x!
x"
x#
x$
x%
x&
$end
